fastaUtils/__init__.py
fastaUtils/encoding.py
fastaUtils/fasta.py
fastaUtils/grammars.py
fastaUtils/profiles.py
fastaUtils/random.py
fastaUtils/remote.py
fastaUtils-3.1.data/scripts/fst-awk
fastaUtils-3.1.data/scripts/fst-cut
fastaUtils-3.1.data/scripts/fst-distance
fastaUtils-3.1.data/scripts/fst-download
fastaUtils-3.1.data/scripts/fst-encode
fastaUtils-3.1.data/scripts/fst-fromstockholm
fastaUtils-3.1.data/scripts/fst-grep
fastaUtils-3.1.data/scripts/fst-logo
fastaUtils-3.1.data/scripts/fst-paste
fastaUtils-3.1.data/scripts/fst-profile
fastaUtils-3.1.data/scripts/fst-random
fastaUtils-3.1.data/scripts/fst-shuf
fastaUtils-3.1.data/scripts/fst-sort
fastaUtils-3.1.data/scripts/fst-split
fastaUtils-3.1.dist-info/LICENCE
fastaUtils-3.1.dist-info/METADATA
fastaUtils-3.1.dist-info/WHEEL
fastaUtils-3.1.dist-info/top_level.txt
fastaUtils-3.1.dist-info/RECORD
