Metadata-Version: 2.1
Name: fastaUtils
Version: 3.1
Summary: fastaUtils
Home-page: https://gitlab.com/LBS-EPFL/code/fastautils/-/tree/v3.0
Author: szamuner
Author-email: stefano.zamuner@protonmail.com
License: MIT
Platform: UNKNOWN
